guacamoleETL/__init__.py
guacamoleETL/load.py
guacamoleETL/main.py
guacamoleETL/test.py
guacamoleETL/tool.py
guacamoleETL/transform.py
improved-guacamole/__init__.py
improved-guacamole/load.py
improved-guacamole/main.py
improved-guacamole/transform.py
guacamoleETL-0.3.0.dist-info/LICENSE
guacamoleETL-0.3.0.dist-info/METADATA
guacamoleETL-0.3.0.dist-info/WHEEL
guacamoleETL-0.3.0.dist-info/top_level.txt
guacamoleETL-0.3.0.dist-info/RECORD
