Metadata-Version: 2.1
Name: guacamoleETL
Version: 0.3.0
Summary: ETL package for AUTO1 challenge
Home-page: https://github.com/chuhsuanlee/guacamoleETL
Author: Chu-Hsuan Lee
Author-email: joseph.chuhsuanlee@gmail.com
License: UNKNOWN
Platform: UNKNOWN
Classifier: Programming Language :: Python :: 3
Classifier: License :: OSI Approved :: MIT License
Classifier: Operating System :: OS Independent
